ptpyrs-0.1.2.dist-info/METADATA
ptpyrs-0.1.2.dist-info/WHEEL
ptpyrs-0.1.2.dist-info/entry_points.txt
ptpyrs-0.1.2.dist-info/licenses/LICENSE-MIT
ptpyrs/__init__.py
ptpyrs/__main__.py
ptpyrs/ptpyrs.abi3.so
ptpyrs-0.1.2.dist-info/RECORD
