Metadata-Version: 2.4
Name: ptpyrs
Version: 0.1.2
Requires-Dist: pytest ; extra == 'dev'
Provides-Extra: dev
License-File: LICENSE-MIT
Requires-Python: >=3.7
